hat/sqlite3/__init__.py
hat/sqlite3/_sqlite3.cpython-38-aarch64-linux-gnu.so
hat_sqlite3-0.5.3.dist-info/LICENSE
hat_sqlite3-0.5.3.dist-info/METADATA
hat_sqlite3-0.5.3.dist-info/WHEEL
hat_sqlite3-0.5.3.dist-info/top_level.txt
hat_sqlite3-0.5.3.dist-info/zip-safe
hat_sqlite3-0.5.3.dist-info/RECORD
