Metadata-Version: 2.1
Name: hat-sqlite3
Version: 0.5.3
Summary: Hat Sqlite3 build
Home-page: https://github.com/hat-open/hat-sqlite3
License: Apache-2.0
Classifier: Programming Language :: Python :: 3
Classifier: License :: OSI Approved :: Apache Software License
Requires-Python: >=3.8
License-File: LICENSE
